kaggle_mcp/__init__.py
kaggle_mcp/server.py
kaggle_mcp/test.py
kaggle_mcp/utils.py
kaggle_mcp-0.1.0.dist-info/METADATA
kaggle_mcp-0.1.0.dist-info/WHEEL
kaggle_mcp-0.1.0.dist-info/entry_points.txt
kaggle_mcp-0.1.0.dist-info/RECORD
