Metadata-Version: 2.4
Name: kaggle-mcp
Version: 0.1.0
Summary: A MCP server for kaggle apis
Author-email: Dixing Xu <i@dex.moe>
Requires-Python: >=3.10
Requires-Dist: diskcache>=5.6.3
Requires-Dist: kaggle>=1.7.4.2
Requires-Dist: mcp>=1.4.1
Requires-Dist: pandas>=2.2.3
Requires-Dist: py7zr>=0.22.0
Requires-Dist: tenacity>=9.0.0
